yasjenkins/__init__.py
yasjenkins/handler.py
yasjenkins-1.0b2.dist-info/METADATA
yasjenkins-1.0b2.dist-info/WHEEL
yasjenkins-1.0b2.dist-info/top_level.txt
yasjenkins-1.0b2.dist-info/RECORD
